ionmob/__init__.py
ionmob/example_data/DB_search_psm.zip
ionmob/example_data/Tenzer-phospho-train_unique_unimod.parquet
ionmob/example_data/Tenzer-phospho-valid_unique_unimod.parquet
ionmob/example_data/Tenzer_unimod.parquet
ionmob/example_data/Zepeda_thunder_unique_unimod.parquet
ionmob/models/__init__.py
ionmob/models/deep_models.py
ionmob/models/low_parametric.py
ionmob/preprocess/__init__.py
ionmob/preprocess/alignment.py
ionmob/preprocess/data.py
ionmob/preprocess/experiment.py
ionmob/pretrained_models/__init__.py
ionmob/pretrained_models/DeepTwoMerModel/keras_metadata.pb
ionmob/pretrained_models/DeepTwoMerModel/saved_model.pb
ionmob/pretrained_models/DeepTwoMerModel/variables/variables.data-00000-of-00001
ionmob/pretrained_models/DeepTwoMerModel/variables/variables.index
ionmob/pretrained_models/GRUPredictor/fingerprint.pb
ionmob/pretrained_models/GRUPredictor/keras_metadata.pb
ionmob/pretrained_models/GRUPredictor/saved_model.pb
ionmob/pretrained_models/GRUPredictor/variables/variables.data-00000-of-00001
ionmob/pretrained_models/GRUPredictor/variables/variables.index
ionmob/pretrained_models/SqrtModel/keras_metadata.pb
ionmob/pretrained_models/SqrtModel/saved_model.pb
ionmob/pretrained_models/SqrtModel/variables/variables.data-00000-of-00001
ionmob/pretrained_models/SqrtModel/variables/variables.index
ionmob/pretrained_models/__pycache__/__init__.cpython-39.pyc
ionmob/pretrained_models/tokenizers/tokenizer-old.json
ionmob/pretrained_models/tokenizers/tokenizer.json
ionmob/pretrained_models/tokenizers/tokenizer_not_unimod.json
ionmob/utilities/__init__.py
ionmob/utilities/chemistry.py
ionmob/utilities/tokenization.py
ionmob/utilities/utility.py
tests/__init__.py
tests/test_chemistry.py
tests/test_custom_layers.py
tests/test_low_parametric.py
tests/test_pretrained_models.py
tests/test_tokenization.py
tests/test_utility.py
ionmob-0.2.2.dist-info/LICENSE
ionmob-0.2.2.dist-info/METADATA
ionmob-0.2.2.dist-info/WHEEL
ionmob-0.2.2.dist-info/top_level.txt
ionmob-0.2.2.dist-info/RECORD
