Metadata-Version: 2.1
Name: ionmob
Version: 0.2.2
Summary: predict peptide collision-cross sections / ion-mobilities
Home-page: UNKNOWN
License: UNKNOWN
Platform: UNKNOWN
Classifier: Programming Language :: Python :: 3.8
Classifier: Programming Language :: Python :: 3.9
Classifier: Programming Language :: Python :: 3.10
Classifier: Programming Language :: Python :: 3.11
Classifier: Programming Language :: Python :: 3.12
Classifier: License :: OSI Approved :: GNU General Public License v3 or later (GPLv3+)
Classifier: Operating System :: OS Independent
Requires-Python: >=3.8
License-File: LICENSE
Requires-Dist: tensorflow (>=2.7)
Requires-Dist: pyopenms (>=1.0)
Requires-Dist: pandas (>=1.1)
Requires-Dist: pyarrow (>=0.5)
Requires-Dist: scipy (>=1.5)
Requires-Dist: scikit-learn (>=1.0.0)
Requires-Dist: h5py (>=3.0.0)
Requires-Dist: biopython (>=1.5)
Requires-Dist: matplotlib (>=3.0)
